PyForSatan/__init__.py
PyForSatan/Base/__init__.py
PyForSatan/Base/base.py
PyForSatan/Base/error.py
PyForSatan/Base/get_config.py
PyForSatan/Base/get_yaml_config.py
PyForSatan/Base/path.py
PyForSatan/Email/__init__.py
PyForSatan/Email/respond.py
PyForSatan/Email/send.py
PyForSatan/LinuxConnect/__init__.py
PyForSatan/LinuxConnect/base_drivers.py
PyForSatan/LinuxConnect/get_info_Linux.py
PyForSatan/Office/__init__.py
PyForSatan/Office/execl_read.py
PyForSatan/Office/execl_write.py
PyForSatan-0.0.2.dist-info/METADATA
PyForSatan-0.0.2.dist-info/WHEEL
PyForSatan-0.0.2.dist-info/top_level.txt
PyForSatan-0.0.2.dist-info/RECORD
