Metadata-Version: 2.1
Name: PyForSatan
Version: 0.0.2
Summary: a tools package
Home-page: https://github.com/satanwuming/PyForSatan
Author: Satan
Author-email: satanwuming@gmail.com
License: UNKNOWN
Platform: UNKNOWN
Classifier: Programming Language :: Python :: 3
Classifier: License :: OSI Approved :: MIT License
Classifier: Operating System :: OS Independent
Requires-Python: >=3.5
Requires-Dist: paramiko (>=2.4.2)
Requires-Dist: openpyxl (>=2.5.6)
Requires-Dist: xlrd (>=1.1.0)
Requires-Dist: PyYAML (>=5.1.2)
